{
  "image_id": "143",
  "bounding_boxes": [
    {
      "image_id": "143",
      "id": "9305",
      "bb": [
        556,
        300,
        69,
        62
      ],
      "class_name": "cup",
      "auto_flg": true
    },
    {
      "image_id": "143",
      "id": "9307",
      "bb": [
        588,
        230,
        47,
        74
      ],
      "class_name": "bottle",
      "auto_flg": true
    },
    {
      "image_id": "143",
      "id": "021(鍋)",
      "bb": [
        606,
        254,
        215,
        115
      ],
      "class_name": "pot",
      "auto_flg": false
    },
    {
      "image_id": "143",
      "id": "9316",
      "bb": [
        656,
        142,
        69,
        118
      ],
      "class_name": "bottle",
      "auto_flg": true
    },
    {
      "image_id": "143",
      "id": "9319",
      "bb": [
        613,
        175,
        86,
        110
      ],
      "class_name": "bottle",
      "auto_flg": true
    },
    {
      "image_id": "143",
      "id": "9329",
      "bb": [
        528,
        326,
        49,
        57
      ],
      "class_name": "bottle",
      "auto_flg": true
    },
    {
      "image_id": "143",
      "id": "001(主人)",
      "bb": [
        640,
        0,
        553,
        900
      ],
      "class_name": "person",
      "auto_flg": false
    },
    {
      "image_id": "143",
      "id": "9389",
      "bb": [
        610,
        218,
        43,
        75
      ],
      "class_name": "bottle",
      "auto_flg": true
    },
    {
      "image_id": "143",
      "id": "9401",
      "bb": [
        763,
        181,
        38,
        56
      ],
      "class_name": "wineglass",
      "auto_flg": true
    },
    {
      "image_id": "143",
      "id": "9406",
      "bb": [
        858,
        173,
        35,
        53
      ],
      "class_name": "wineglass",
      "auto_flg": true
    },
    {
      "image_id": "143",
      "id": "007(豆乳)",
      "bb": [
        1263,
        289,
        116,
        146
      ],
      "class_name": "soya_milk",
      "auto_flg": false
    },
    {
      "image_id": "143",
      "id": "tv",
      "bb": [
        665,
        0,
        221,
        168
      ],
      "class_name": "bowl",
      "auto_flg": true
    },
    {
      "image_id": "143",
      "id": "9442",
      "bb": [
        831,
        173,
        33,
        65
      ],
      "class_name": "wineglass",
      "auto_flg": true
    },
    {
      "image_id": "143",
      "id": "9500",
      "bb": [
        1350,
        129,
        155,
        48
      ],
      "class_name": "place_mat",
      "auto_flg": true
    },
    {
      "image_id": "143",
      "id": "9511",
      "bb": [
        1282,
        108,
        34,
        45
      ],
      "class_name": "vase",
      "auto_flg": true
    },
    {
      "image_id": "143",
      "id": "9519",
      "bb": [
        1278,
        69,
        63,
        73
      ],
      "class_name": "flowerpot",
      "auto_flg": true
    },
    {
      "image_id": "143",
      "id": "9548",
      "bb": [
        1500,
        131,
        78,
        63
      ],
      "class_name": "crock_pot",
      "auto_flg": true
    },
    {
      "image_id": "143",
      "id": "9555",
      "bb": [
        1277,
        139,
        24,
        19
      ],
      "class_name": "apple",
      "auto_flg": true
    },
    {
      "image_id": "143",
      "id": "9566",
      "bb": [
        1278,
        69,
        64,
        46
      ],
      "class_name": "flower_arrangement",
      "auto_flg": true
    },
    {
      "image_id": "143",
      "id": "009(包丁)",
      "bb": [
        1445,
        502,
        141,
        85
      ],
      "class_name": "knife",
      "auto_flg": false
    },
    {
      "image_id": "143",
      "id": "9621",
      "bb": [
        1281,
        156,
        26,
        17
      ],
      "class_name": "apple",
      "auto_flg": true
    },
    {
      "image_id": "143",
      "id": "9625",
      "bb": [
        1266,
        148,
        19,
        16
      ],
      "class_name": "apple",
      "auto_flg": true
    },
    {
      "image_id": "143",
      "id": "9629",
      "bb": [
        1174,
        71,
        104,
        45
      ],
      "class_name": "chair",
      "auto_flg": true
    },
    {
      "image_id": "143",
      "id": "9889",
      "bb": [
        455,
        791,
        165,
        136
      ],
      "class_name": "plastic_bag",
      "auto_flg": true
    },
    {
      "image_id": "143",
      "id": "9922",
      "bb": [
        1506,
        704,
        99,
        33
      ],
      "class_name": "handle",
      "auto_flg": true
    },
    {
      "image_id": "143",
      "id": "10015",
      "bb": [
        661,
        144,
        19,
        13
      ],
      "class_name": "bottle_cap",
      "auto_flg": true
    },
    {
      "image_id": "143",
      "id": "10040",
      "bb": [
        1849,
        95,
        41,
        19
      ],
      "class_name": "vent",
      "auto_flg": true
    },
    {
      "image_id": "143",
      "id": "10047",
      "bb": [
        1432,
        8,
        32,
        49
      ],
      "class_name": "figurine",
      "auto_flg": true
    },
    {
      "image_id": "143",
      "id": "10055",
      "bb": [
        795,
        168,
        38,
        62
      ],
      "class_name": "wineglass",
      "auto_flg": true
    },
    {
      "image_id": "143",
      "id": "10072",
      "bb": [
        629,
        177,
        23,
        14
      ],
      "class_name": "bottle_cap",
      "auto_flg": true
    },
    {
      "image_id": "143",
      "id": "10083",
      "bb": [
        733,
        180,
        37,
        63
      ],
      "class_name": "wineglass",
      "auto_flg": true
    },
    {
      "image_id": "143",
      "id": "10092",
      "bb": [
        1816,
        84,
        12,
        10
      ],
      "class_name": "wall_socket",
      "auto_flg": true
    },
    {
      "image_id": "143",
      "id": "10094",
      "bb": [
        713,
        179,
        36,
        64
      ],
      "class_name": "wineglass",
      "auto_flg": true
    },
    {
      "image_id": "143",
      "id": "10169",
      "bb": [
        0,
        534,
        605,
        543
      ],
      "class_name": "cabinet",
      "auto_flg": true
    },
    {
      "image_id": "143",
      "id": "10171",
      "bb": [
        1259,
        11,
        67,
        28
      ],
      "class_name": "projector",
      "auto_flg": true
    },
    {
      "image_id": "143",
      "id": "10210",
      "bb": [
        642,
        200,
        382,
        478
      ],
      "class_name": "shirt",
      "auto_flg": true
    },
    {
      "image_id": "143",
      "id": "10215",
      "bb": [
        1359,
        382,
        547,
        254
      ],
      "class_name": "sink",
      "auto_flg": true
    },
    {
      "image_id": "143",
      "id": "002(ロボット)",
      "bb": [
        736,
        950,
        432,
        133
      ],
      "class_name": "person",
      "auto_flg": false
    },
    {
      "image_id": "143",
      "id": "10235",
      "bb": [
        1726,
        391,
        103,
        66
      ],
      "class_name": "potholder",
      "auto_flg": true
    },
    {
      "image_id": "143",
      "id": "10241",
      "bb": [
        1558,
        381,
        130,
        74
      ],
      "class_name": "hand_towel",
      "auto_flg": true
    },
    {
      "image_id": "143",
      "id": "10242",
      "bb": [
        812,
        565,
        282,
        235
      ],
      "class_name": "short_pants",
      "auto_flg": true
    },
    {
      "image_id": "143",
      "id": "10243",
      "bb": [
        1859,
        197,
        60,
        69
      ],
      "class_name": "chair",
      "auto_flg": true
    },
    {
      "image_id": "143",
      "id": "10245",
      "bb": [
        1638,
        105,
        276,
        130
      ],
      "class_name": "desk",
      "auto_flg": true
    },
    {
      "image_id": "143",
      "id": "10249",
      "bb": [
        1211,
        649,
        624,
        208
      ],
      "class_name": "drawer",
      "auto_flg": true
    },
    {
      "image_id": "143",
      "id": "10264",
      "bb": [
        951,
        840,
        109,
        55
      ],
      "class_name": "shoe",
      "auto_flg": true
    },
    {
      "image_id": "143",
      "id": "10265",
      "bb": [
        1385,
        269,
        85,
        100
      ],
      "class_name": "cup",
      "auto_flg": true
    },
    {
      "image_id": "143",
      "id": "005(皮むき)",
      "bb": [
        1282,
        443,
        54,
        79
      ],
      "class_name": "peeler_(tool_for_fruit_and_vegetables)",
      "auto_flg": false
    },
    {
      "image_id": "143",
      "id": "10274",
      "bb": [
        0,
        677,
        59,
        87
      ],
      "class_name": "cup",
      "auto_flg": true
    },
    {
      "image_id": "143",
      "id": "10279",
      "bb": [
        1020,
        611,
        266,
        176
      ],
      "class_name": "drawer",
      "auto_flg": true
    },
    {
      "image_id": "143",
      "id": "10282",
      "bb": [
        1307,
        111,
        40,
        47
      ],
      "class_name": "cup",
      "auto_flg": true
    },
    {
      "image_id": "143",
      "id": "10285",
      "bb": [
        1089,
        539,
        236,
        111
      ],
      "class_name": "drawer",
      "auto_flg": true
    },
    {
      "image_id": "143",
      "id": "10286",
      "bb": [
        1087,
        630,
        82,
        25
      ],
      "class_name": "handle",
      "auto_flg": true
    },
    {
      "image_id": "143",
      "id": "10290",
      "bb": [
        1352,
        0,
        72,
        58
      ],
      "class_name": "printer",
      "auto_flg": true
    }
  ],
  "caption": {
    "image_id": "143",
    "id": "143",
    "text": "<<<あ0>>><<<じゃあ0>>>、<<<シチュー>>><<<作る>>><<<の0>>>を<<<手伝ってくれる>>>？\r\n<<<分かりました0>>>。\r\n<<<あららー>>><<<牛乳0>>>が<<<ありません>>>ね。\r\n<<<あ1>>><<<買う>>><<<の1>>><<<忘れてた>>>。<<<んー>>><<<代用できそうな>>><<<もの>>><<<何>>>か<<<ある0>>>？\r\n<<<豆乳0>>>なら<<<あります>>>よ。<<<牛乳1>>>が<<<ない>>><<<場合>>>は<<<豆乳1>>>で<<<代用する>>><<<こと>>>が<<<可能です>>>。\r\n<<<うん0>>><<<うん1>>>\r\n<<<おー>>><<<じゃあ1>>>、<<<それ>>>を<<<使おう>>>。\r\n<<<じゃあ2>>>、<<<とりあえず>>>、<<<ここ0>>>に<<<ある1>>><<<野菜0>>>を<<<切ってくれる>>>？\r\n<<<はい0>>><<<了解しました>>>。<<<最初に>>><<<皮0>>>を<<<剥きます>>>ね。\r\n<<<まず>>>、<<<剥かなきゃ>>>ね。\r\n<<<うん2>>><<<うん3>>>\r\n<<<うん4>>>\r\n<<<じゃあ3>>>、<<<皮1>>><<<むき>>>は<<<ここ1>>>に<<<ある2>>>からね。\r\n<<<はい1>>><<<お借りします>>>。\r\n<<<うん5>>>\r\n<<<切ったら>>><<<ここ2>>>に<<<入れていく>>>ね。\r\n<<<はい2>>>\r\n<<<よいしょ0>>>。\r\n<<<じゃあ4>>>、<<<私>>>も<<<手伝う>>>ね。<<<ちょっと>>>、<<<いい>>>？<<<ごめん>>>ね。\r\n<<<はい3>>>\r\n<<<助かります>>>。\r\n<<<うん6>>>\r\n<<<よいしょ1>>>。\r\n<<<はい4>>><<<ありがとう0>>>。<<<じゃあ5>>>、<<<切っていく>>>ね。\r\n<<<よいしょ2>>>。<<<切った0>>><<<野菜1>>>は<<<ここ3>>>に<<<入れます>>>。\r\n<<<人参>>>も<<<お願いできます>>>か？\r\n<<<うん7>>><<<もちろん>>>。\r\n<<<よいしょ3>>>。\r\n<<<えーっと>>>\r\n<<<よいしょ4>>>。\r\n<<<じゃあ6>>>、<<<切った1>>><<<野菜2>>>は<<<ここ4>>>に<<<入れて>>>。\r\n<<<あと>>>、<<<鶏肉0>>><<<取ってくれる>>>かな？\r\n<<<鶏肉1>>>ですね。\r\n<<<うん8>>>\r\n<<<冷蔵>>><<<庫>>>から<<<取ってきます>>>。\r\n<<<うん9>>><<<お願い>>>。\r\n<<<どうぞ>>>。\r\n<<<あ2>>><<<ありがとう1>>>。<<<じゃあ7>>>、<<<鶏肉2>>>を<<<炒める>>>から、<<<この>>><<<野菜3>>>、<<<チンしてきてくれる>>>？\r\n<<<はい5>>><<<分かりました1>>>。<<<何分>>><<<温めましょう>>>か？\r\n<<<うん10>>>\r\n<<<そう>>>だね<<<五分0>>>で<<<よろしく>>>。\r\n<<<五分1>>>ですね。<<<分かりました2>>>。\r\n<<<うん11>>>"
  },
  "relations": [],
  "i2t_relations": []
}
