{
  "image_id": "026",
  "bounding_boxes": [
    {
      "image_id": "026",
      "id": "007(水道)",
      "bb": [
        967,
        255,
        134,
        213
      ],
      "class_name": "water_faucet",
      "auto_flg": false
    },
    {
      "image_id": "026",
      "id": "001(主人)",
      "bb": [
        -5,
        44,
        680,
        727
      ],
      "class_name": "person",
      "auto_flg": false
    },
    {
      "image_id": "026",
      "id": "1343",
      "bb": [
        1101,
        372,
        39,
        67
      ],
      "class_name": "bottle",
      "auto_flg": true
    },
    {
      "image_id": "026",
      "id": "1348",
      "bb": [
        763,
        349,
        630,
        505
      ],
      "class_name": "sink",
      "auto_flg": true
    },
    {
      "image_id": "026",
      "id": "tv",
      "bb": [
        1024,
        -1,
        140,
        114
      ],
      "class_name": "basket",
      "auto_flg": true
    },
    {
      "image_id": "026",
      "id": "sponge",
      "bb": [
        1288,
        582,
        89,
        117
      ],
      "class_name": "cover",
      "auto_flg": true
    },
    {
      "image_id": "026",
      "id": "1434",
      "bb": [
        710,
        110,
        33,
        63
      ],
      "class_name": "bottle",
      "auto_flg": true
    },
    {
      "image_id": "026",
      "id": "004(青縁カップ)",
      "bb": [
        919,
        181,
        56,
        54
      ],
      "class_name": "cup",
      "auto_flg": false
    },
    {
      "image_id": "026",
      "id": "1442",
      "bb": [
        732,
        109,
        32,
        60
      ],
      "class_name": "bottle",
      "auto_flg": true
    },
    {
      "image_id": "026",
      "id": "1459",
      "bb": [
        750,
        92,
        47,
        76
      ],
      "class_name": "bottle",
      "auto_flg": true
    },
    {
      "image_id": "026",
      "id": "1479",
      "bb": [
        794,
        63,
        40,
        94
      ],
      "class_name": "bottle",
      "auto_flg": true
    },
    {
      "image_id": "026",
      "id": "008(白カップ)",
      "bb": [
        989,
        454,
        75,
        64
      ],
      "class_name": "cup",
      "auto_flg": false
    },
    {
      "image_id": "026",
      "id": "1536",
      "bb": [
        1153,
        22,
        83,
        65
      ],
      "class_name": "monitor_(computer_equipment) computer_monitor",
      "auto_flg": true
    },
    {
      "image_id": "026",
      "id": "005(かご)",
      "bb": [
        821,
        162,
        275,
        201
      ],
      "class_name": "basket",
      "auto_flg": false
    },
    {
      "image_id": "026",
      "id": "1550",
      "bb": [
        800,
        62,
        14,
        6
      ],
      "class_name": "bottle_cap",
      "auto_flg": true
    },
    {
      "image_id": "026",
      "id": "1559",
      "bb": [
        1022,
        1,
        143,
        120
      ],
      "class_name": "television_set",
      "auto_flg": true
    },
    {
      "image_id": "026",
      "id": "1561",
      "bb": [
        1506,
        246,
        42,
        29
      ],
      "class_name": "tomato",
      "auto_flg": true
    },
    {
      "image_id": "026",
      "id": "1573",
      "bb": [
        1548,
        234,
        41,
        27
      ],
      "class_name": "tomato",
      "auto_flg": true
    },
    {
      "image_id": "026",
      "id": "1576",
      "bb": [
        1483,
        63,
        49,
        23
      ],
      "class_name": "bowl",
      "auto_flg": true
    },
    {
      "image_id": "026",
      "id": "1577",
      "bb": [
        1440,
        167,
        183,
        55
      ],
      "class_name": "computer_keyboard",
      "auto_flg": true
    },
    {
      "image_id": "026",
      "id": "1578",
      "bb": [
        1524,
        230,
        396,
        278
      ],
      "class_name": "dining_table",
      "auto_flg": true
    },
    {
      "image_id": "026",
      "id": "1582",
      "bb": [
        1550,
        144,
        94,
        61
      ],
      "class_name": "chair",
      "auto_flg": true
    },
    {
      "image_id": "026",
      "id": "1594",
      "bb": [
        1606,
        211,
        80,
        69
      ],
      "class_name": "cup",
      "auto_flg": true
    },
    {
      "image_id": "026",
      "id": "1596",
      "bb": [
        1608,
        163,
        117,
        58
      ],
      "class_name": "flower_arrangement",
      "auto_flg": true
    },
    {
      "image_id": "026",
      "id": "1598",
      "bb": [
        1508,
        274,
        271,
        304
      ],
      "class_name": "chair",
      "auto_flg": true
    },
    {
      "image_id": "026",
      "id": "1608",
      "bb": [
        1592,
        276,
        71,
        23
      ],
      "class_name": "lemon",
      "auto_flg": true
    },
    {
      "image_id": "026",
      "id": "1610",
      "bb": [
        1702,
        270,
        217,
        107
      ],
      "class_name": "place_mat",
      "auto_flg": true
    },
    {
      "image_id": "026",
      "id": "1625",
      "bb": [
        1766,
        214,
        153,
        110
      ],
      "class_name": "chair",
      "auto_flg": true
    },
    {
      "image_id": "026",
      "id": "1681",
      "bb": [
        668,
        150,
        37,
        36
      ],
      "class_name": "jar",
      "auto_flg": true
    },
    {
      "image_id": "026",
      "id": "006(布巾)",
      "bb": [
        815,
        192,
        69,
        74
      ],
      "class_name": "dishtowel",
      "auto_flg": false
    },
    {
      "image_id": "026",
      "id": "1708",
      "bb": [
        890,
        128,
        33,
        70
      ],
      "class_name": "wineglass",
      "auto_flg": true
    },
    {
      "image_id": "026",
      "id": "010(皿２枚)",
      "bb": [
        983,
        649,
        196,
        163
      ],
      "class_name": "plate",
      "auto_flg": false
    },
    {
      "image_id": "026",
      "id": "1788",
      "bb": [
        642,
        155,
        26,
        36
      ],
      "class_name": "bottle",
      "auto_flg": true
    },
    {
      "image_id": "026",
      "id": "009(蓋)",
      "bb": [
        1029,
        621,
        217,
        167
      ],
      "class_name": "cover",
      "auto_flg": false
    },
    {
      "image_id": "026",
      "id": "003(ポット)",
      "bb": [
        728,
        850,
        358,
        229
      ],
      "class_name": "kettle",
      "auto_flg": false
    },
    {
      "image_id": "026",
      "id": "002(ロボット)",
      "bb": [
        660,
        952,
        535,
        133
      ],
      "class_name": "person",
      "auto_flg": false
    },
    {
      "image_id": "026",
      "id": "1880",
      "bb": [
        659,
        1025,
        99,
        53
      ],
      "class_name": "person",
      "auto_flg": true
    },
    {
      "image_id": "026",
      "id": "1906",
      "bb": [
        1239,
        145,
        26,
        48
      ],
      "class_name": "wall_socket",
      "auto_flg": true
    },
    {
      "image_id": "026",
      "id": "1921",
      "bb": [
        1050,
        271,
        53,
        39
      ],
      "class_name": "bottle_cap",
      "auto_flg": true
    },
    {
      "image_id": "026",
      "id": "1926",
      "bb": [
        1099,
        374,
        40,
        132
      ],
      "class_name": "bottle",
      "auto_flg": true
    },
    {
      "image_id": "026",
      "id": "1931",
      "bb": [
        466,
        409,
        76,
        69
      ],
      "class_name": "tissue_paper",
      "auto_flg": true
    },
    {
      "image_id": "026",
      "id": "1933",
      "bb": [
        1606,
        162,
        124,
        115
      ],
      "class_name": "flowerpot",
      "auto_flg": true
    }
  ],
  "caption": {
    "image_id": "026",
    "id": "026",
    "text": "<<<よっし>>>、<<<洗い>>><<<物>>>が<<<終わったら0>>>、<<<コーヒー>>>でも<<<飲もう>>>かな。\r\n<<<それ0>>>なら、<<<お湯0>>>を<<<沸かしましょう>>>か？\r\n<<<うん0>>><<<お願いする>>>よ。<<<えっ0>>>と<<<それ1>>>を<<<使ってくれる>>>？\r\n<<<はい0>>>\r\n<<<水道>>>を<<<使わせて下さい>>>。\r\n<<<あ>>><<<ごめん>>>。<<<ちょっと>>>、<<<待って>>>ね。\r\n<<<よいしょ>>>。\r\n<<<はい1>>>、<<<どうぞ>>>。\r\n<<<ありがとうございます>>>。\r\n<<<沸く>>>まで、<<<少し>>><<<お待ち下さい>>>。\r\n<<<うん1>>><<<ありがとう0>>>。<<<えっ1>>>と<<<マグカップ0>>>も<<<用意しておいてもらえる>>>かな。\r\n<<<はい2>>>\r\n<<<マグカップ1>>>を<<<出しておきます>>>ね。\r\n<<<うん2>>><<<お願い0>>>。\r\n<<<洗い終わった>>><<<の>>>を、<<<かご>>>に<<<入れていってくれる>>>？\r\n<<<はい3>>>\r\n<<<はい4>>>。\r\n<<<並べておきます>>>ね。\r\n<<<うん3>>><<<お願い1>>>。\r\n<<<じゃ>>>、<<<それ2>>>が<<<終わったら1>>>、<<<布巾>>>で<<<この>>><<<あたり>>>も<<<拭いといてくれる>>>かな？\r\n<<<はい5>>><<<分かりました>>>。\r\n<<<調理>>><<<台>>>を<<<拭いておきます>>>ね。\r\n<<<うん4>>><<<ありがとう1>>>。\r\n<<<あと>>>、<<<あの>>><<<ポット>>>の<<<方>>>も<<<お願い2>>>。\r\n<<<はい6>>><<<お湯1>>>が<<<沸いたら>>>、<<<お知らせします>>>ね。"
  },
  "relations": [],
  "i2t_relations": []
}
