{
  "image_id": "014",
  "bounding_boxes": [
    {
      "image_id": "014",
      "id": "1422",
      "bb": [
        3,
        607,
        115,
        58
      ],
      "class_name": "pocketknife",
      "auto_flg": true
    },
    {
      "image_id": "014",
      "id": "1410",
      "bb": [
        457,
        350,
        170,
        47
      ],
      "class_name": "vent",
      "auto_flg": true
    },
    {
      "image_id": "014",
      "id": "1397",
      "bb": [
        819,
        130,
        192,
        170
      ],
      "class_name": "bowl",
      "auto_flg": true
    },
    {
      "image_id": "014",
      "id": "1394",
      "bb": [
        420,
        431,
        250,
        226
      ],
      "class_name": "frying_pan",
      "auto_flg": true
    },
    {
      "image_id": "014",
      "id": "1375",
      "bb": [
        -2,
        559,
        128,
        66
      ],
      "class_name": "knife",
      "auto_flg": true
    },
    {
      "image_id": "014",
      "id": "1347",
      "bb": [
        -3,
        518,
        139,
        69
      ],
      "class_name": "knife",
      "auto_flg": true
    },
    {
      "image_id": "014",
      "id": "1343",
      "bb": [
        1095,
        238,
        652,
        402
      ],
      "class_name": "sink",
      "auto_flg": true
    },
    {
      "image_id": "014",
      "id": "1339",
      "bb": [
        902,
        1024,
        27,
        22
      ],
      "class_name": "button",
      "auto_flg": true
    },
    {
      "image_id": "014",
      "id": "1330",
      "bb": [
        1332,
        276,
        148,
        52
      ],
      "class_name": "sponge",
      "auto_flg": true
    },
    {
      "image_id": "014",
      "id": "1316",
      "bb": [
        686,
        331,
        77,
        119
      ],
      "class_name": "scissors",
      "auto_flg": true
    },
    {
      "image_id": "014",
      "id": "1313",
      "bb": [
        457,
        607,
        65,
        37
      ],
      "class_name": "tag",
      "auto_flg": true
    },
    {
      "image_id": "014",
      "id": "1307",
      "bb": [
        1332,
        104,
        69,
        31
      ],
      "class_name": "soap",
      "auto_flg": true
    },
    {
      "image_id": "014",
      "id": "004(テーブル)",
      "bb": [
        569,
        -16,
        625,
        142
      ],
      "class_name": "dining_table",
      "auto_flg": false
    },
    {
      "image_id": "014",
      "id": "1238",
      "bb": [
        685,
        497,
        40,
        35
      ],
      "class_name": "bottle_cap",
      "auto_flg": true
    },
    {
      "image_id": "014",
      "id": "1188",
      "bb": [
        583,
        576,
        99,
        73
      ],
      "class_name": "handle",
      "auto_flg": true
    },
    {
      "image_id": "014",
      "id": "1148",
      "bb": [
        683,
        242,
        75,
        88
      ],
      "class_name": "soap",
      "auto_flg": true
    },
    {
      "image_id": "014",
      "id": "1134",
      "bb": [
        458,
        674,
        71,
        170
      ],
      "class_name": "handle",
      "auto_flg": true
    },
    {
      "image_id": "014",
      "id": "1133",
      "bb": [
        1106,
        197,
        278,
        224
      ],
      "class_name": "faucet",
      "auto_flg": true
    },
    {
      "image_id": "014",
      "id": "1127",
      "bb": [
        733,
        458,
        95,
        98
      ],
      "class_name": "jar",
      "auto_flg": true
    },
    {
      "image_id": "014",
      "id": "1113",
      "bb": [
        685,
        497,
        84,
        110
      ],
      "class_name": "bottle",
      "auto_flg": true
    },
    {
      "image_id": "014",
      "id": "1093",
      "bb": [
        -8,
        365,
        186,
        119
      ],
      "class_name": "grater",
      "auto_flg": true
    },
    {
      "image_id": "014",
      "id": "997",
      "bb": [
        -3,
        704,
        160,
        68
      ],
      "class_name": "bottle",
      "auto_flg": true
    },
    {
      "image_id": "014",
      "id": "963",
      "bb": [
        180,
        503,
        174,
        179
      ],
      "class_name": "mouse_(computer_equipment)",
      "auto_flg": true
    },
    {
      "image_id": "014",
      "id": "002(ロボット)",
      "bb": [
        550,
        504,
        994,
        593
      ],
      "class_name": "person",
      "auto_flg": false
    }
  ],
  "caption": {
    "image_id": "014",
    "id": "014",
    "text": "<<<おはよう>>>。<<<今日0>>>は<<<いい0>>><<<天気0>>>だね。\r\n<<<おはようございます>>>。<<<いい1>>><<<天気1>>>ですね。<<<コーヒー>>>は<<<いかがです0>>>か？\r\n<<<じゃあ0>>>、<<<カフェオレ>>><<<お願い>>>。\r\n<<<分かりました0>>>。\r\n<<<あー>>><<<そう0>>><<<いえば>>>、<<<今日1>>>は<<<夕方>>>まで<<<出かけるんだ>>>けど、<<<天気2>>>は<<<もつ>>>かな？\r\n<<<はい0>>>\r\n<<<そう1>>>ですねー<<<確認しましょう>>>。\r\n<<<うん0>>><<<ありがとう>>>。<<<天気3>>>は<<<もつみたいだ>>>ね。<<<じゃあ1>>>、<<<自転車>>>で<<<行こう>>>かな。\r\n<<<そう2>>>ですね<<<では、>>><<<カバン>>>は<<<リュック0>>>が<<<いかがです1>>>か？\r\n<<<うん1>>><<<リュック1>>>が<<<いい2>>>ね。\r\n<<<はい1>>>\r\n<<<そっち>>>の<<<テーブル>>>に<<<置いてある>>>から、<<<持ってきてくれる>>>？\r\n<<<これ>>>ですね。<<<あと0>>>は<<<何>>>か<<<必要な>>><<<もの>>>は<<<あります>>>か？\r\n<<<うん2>>><<<あと1>>>は<<<自分>>>で<<<やる>>>から<<<大丈夫>>>。\r\n<<<分かりました1>>>。"
  },
  "relations": [],
  "i2t_relations": []
}
